pflake8/__init__.py
pflake8/__main__.py
pyproject_flake8-6.1.0.dist-info/entry_points.txt
pyproject_flake8-6.1.0.dist-info/LICENSE
pyproject_flake8-6.1.0.dist-info/WHEEL
pyproject_flake8-6.1.0.dist-info/METADATA
pyproject_flake8-6.1.0.dist-info/RECORD
