Metadata-Version: 2.1
Name: pyproject-flake8
Version: 6.1.0
Summary: pyproject-flake8 (`pflake8`), a monkey patching wrapper to connect flake8 with pyproject.toml configuration 
Author-email: Christian Sachs <sachs.christian@gmail.com>
Requires-Python: >=3.8.1
Requires-Dist: tomli; python_version < '3.11'
Requires-Dist: flake8 == 6.1.0
Project-URL: Home, https://github.com/csachs/pyproject-flake8
